pyrdt/__init__.py
pyrdt/atom.py
pyrdt/combo.py
pyrdt/math.py
pyrdt/stat.py
pywfz/__init__.py
pywfz/myMath.py
pywfz/sql.py
pywfz/util.py
pywfz1/__init__.py
pywfz1/myMath.py
pywfz1-1.0.0.dist-info/LICENSE
pywfz1-1.0.0.dist-info/METADATA
pywfz1-1.0.0.dist-info/WHEEL
pywfz1-1.0.0.dist-info/top_level.txt
pywfz1-1.0.0.dist-info/RECORD
